django_hfut_auth-0.1.2.dist-info/DESCRIPTION.rst
django_hfut_auth-0.1.2.dist-info/METADATA
django_hfut_auth-0.1.2.dist-info/RECORD
django_hfut_auth-0.1.2.dist-info/WHEEL
django_hfut_auth-0.1.2.dist-info/metadata.json
django_hfut_auth-0.1.2.dist-info/top_level.txt
hfut_auth/__init__.py
hfut_auth/apps.py
hfut_auth/backends.py
hfut_auth/forms.py
hfut_auth/log.py
hfut_auth/settings.py
hfut_auth/signals.py
hfut_auth/tests.py
