Metadata-Version: 2.0
Name: django-hfut-auth
Version: 0.1.2
Summary: 使用合工大教务接口进行用户身份认, 支持合肥校区和宣城校区
Home-page: https://github.com/er1iang/django-hfut-auth
Author: erliang
Author-email: dev@erliang.me
License: MIT license
Keywords: hfut_auth
Platform: UNKNOWN
Classifier: Development Status :: 2 - Pre-Alpha
Classifier: Intended Audience :: Developers
Classifier: License :: OSI Approved :: MIT License
Classifier: Programming Language :: Python :: 2
Classifier: Programming Language :: Python :: 2.7
Classifier: Programming Language :: Python :: 3
Classifier: Programming Language :: Python :: 3.4
Classifier: Programming Language :: Python :: 3.5
Requires-Dist: django (>=1.9)
Requires-Dist: hfut (>=1.4.1)
